{
    "version": "0.2.14",
    "architecture": {
        "64bit": {
            "url": "https://github.com/webb1es/dotenvify/releases/download/v0.2.14/dotenvify_0.2.14_windows_amd64.zip",
            "bin": [
                "dotenvify.exe"
            ],
            "hash": "ebf6166d4dc00884e2378897b25c8eb68a0a5deae2170aaeff0533d203278eb8"
        }
    },
    "homepage": "https://github.com/webb1es/dotenvify",
    "license": "MIT",
    "description": "Convert key-value pairs to environment variables"
}